neurostates/__init__.py
neurostates/core/__init__.py
neurostates/core/classification.py
neurostates/core/clustering.py
neurostates/core/connectivity.py
neurostates/core/utils.py
neurostates/core/window.py
neurostates-0.1.2.dist-info/licenses/LICENSE.txt
neurostates-0.1.2.dist-info/METADATA
neurostates-0.1.2.dist-info/WHEEL
neurostates-0.1.2.dist-info/top_level.txt
neurostates-0.1.2.dist-info/RECORD
