Metadata-Version: 2.4
Name: neurostates
Version: 0.1.2
Summary: Neurostates is a tool for analyzing patterns of functional connectivity in EEG and fMRI.
Author-email: Gabriel Della Bella <dellabellagabriel@gmail.com>, Natalia Rodriguez <natirodriguez114@gmail.com>
License: Copyright (c) 2024, Della Bella, Gabriel; Rodriguez, Natalia
Keywords: brain,functional,connectivity,eeg,fmri
Requires-Python: >=3.9
License-File: LICENSE.txt
Requires-Dist: numpy<2.0,>=1.0
Requires-Dist: scipy
Requires-Dist: scikit-learn
Dynamic: license-file
